mlopscli/__init__.py
mlopscli/cli.py
mlopscli/constants.py
mlopscli/dag_visualizer.py
mlopscli/dashboard.py
mlopscli/parser.py
mlopscli/pipeline.py
mlopscli/runner.py
mlopscli-0.1.4.dist-info/METADATA
mlopscli-0.1.4.dist-info/WHEEL
mlopscli-0.1.4.dist-info/entry_points.txt
mlopscli-0.1.4.dist-info/RECORD
